pynads/__init__.py
pynads/_utils.py
pynads/_version.py
pynads/nads.py
pynads/nads_bind.cpython-39-x86_64-linux-gnu.so
pynads-0.1.5.dist-info/LICENSE
pynads-0.1.5.dist-info/METADATA
pynads-0.1.5.dist-info/WHEEL
pynads-0.1.5.dist-info/top_level.txt
pynads-0.1.5.dist-info/RECORD
