Metadata-Version: 2.1
Name: pynads
Version: 0.1.5
Summary: Python bindings to `nads`, a C++ number-of-almost-d-simplices computer
Home-page: https://github.com/flomlo/pynads
Author: Florian Unger
Author-email: florian.unger@posteo.net
License: GPLv3
Platform: UNKNOWN
Classifier: Intended Audience :: Science/Research
Classifier: Intended Audience :: Developers
Classifier: License :: OSI Approved :: GNU General Public License v3 (GPLv3)
Classifier: Programming Language :: Python :: 3
Classifier: Programming Language :: C++
Classifier: Operating System :: POSIX :: Linux
Requires-Python: >=3.6
Requires-Dist: numpy (>=1.17.0)
